ct_counterfactuals/__init__.py
ct_counterfactuals/ae.py
ct_counterfactuals/datasets.py
ct_counterfactuals/classifiers/__init__.py
ct_counterfactuals/classifiers/lungmask/__init__.py
ct_counterfactuals/classifiers/lungmask/resunet.py
ct_counterfactuals/classifiers/phecode/__init__.py
ct_counterfactuals/classifiers/phecode/classes.csv
ct_counterfactuals/classifiers/phecode/classes.py
ct_counterfactuals/classifiers/phecode/i3res.py
ct_counterfactuals/classifiers/phecode/inflate.py
ct_counterfactuals/classifiers/phecode/window_level.py
ct_counterfactuals/classifiers/phecode/data/Phecode_map_v1_2_icd10cm_beta.csv
ct_counterfactuals/classifiers/phecode/data/phecode_icd9_rolled.csv
ct_counterfactuals-0.0.4.dist-info/METADATA
ct_counterfactuals-0.0.4.dist-info/WHEEL
ct_counterfactuals-0.0.4.dist-info/top_level.txt
ct_counterfactuals-0.0.4.dist-info/RECORD
