Metadata-Version: 2.1
Name: ct-counterfactuals
Version: 0.0.4
Summary: Models and methods to generate counterfactuals for computed tomography scans
Home-page: https://github.com/ieee8023/ct-counterfactuals
Author: Joseph Paul Cohen
Author-email: joseph@josephpcohen.com
Classifier: Programming Language :: Python :: 3
Classifier: License :: OSI Approved :: Apache Software License
Classifier: Operating System :: OS Independent
Requires-Python: >=3.6
Requires-Dist: scikit-image
Requires-Dist: numpy
Requires-Dist: tqdm
Requires-Dist: pandas
Requires-Dist: torchxrayvision
Requires-Dist: latentshift
Requires-Dist: omegaconf
Requires-Dist: monai
